spatial_index.cpython-36m-darwin.so
SpatialIndex/__init__.py
spatial_index-1.1.0.dist-info/DESCRIPTION.rst
spatial_index-1.1.0.dist-info/METADATA
spatial_index-1.1.0.dist-info/RECORD
spatial_index-1.1.0.dist-info/WHEEL
spatial_index-1.1.0.dist-info/metadata.json
spatial_index-1.1.0.dist-info/top_level.txt
