Metadata-Version: 2.0
Name: spatial-index
Version: 1.1.0
Summary: Library for generating DBMS spatial index constraints.
Home-page: https://github.com/Caltech-IPAC/SpatialIndex
Author: John Good
Author-email: jcg@ipac.caltech.edu
License: LICENSE.txt
Keywords: astronomy database spatial-index
Platform: UNKNOWN
